UseData: True
# How should we choose a build? Cycle is the only option for now
BuildSelection: Cycle
# For each Race / Opponent ID choose a build selection
BuildChoices:
    # test_123 is active if Debug: True (set via a `config.yml` file)
    test_123:
        BotName: Test
        Cycle:
            - PhoenixEconomic
            # - AdeptVoidray
            # - OneBaseTempests

    Protoss:
        BotName: ProtossRace
        Cycle:
            - AdeptOracle

    Random:
        BotName: RandomRace
        Cycle:
            - OneBaseTempests

    Terran:
        BotName: TerranRace
        Cycle:
            - PhoenixEconomic

    Zerg:
        BotName: ZergRace
        Cycle:
            - AdeptVoidray

Builds:
    AdeptOracle:
        ConstantWorkerProductionTill: 23
        AutoSupplyAtSupply: 44
        OpeningBuildOrder:
            - 13 pylon @ ramp
            - 14 gate @ ramp
            - 15 chrono @ nexus
            - 16 gas
            - 15 worker_scout:
                [ nat, enemy_spawn ]
            - 17 gate @ ramp
            - 18 core
            - 18 gas
            - 20 pylon
            - 21 warpgateresearch
            - 21 adept *2
            # - 22 chrono @ core
            - 22 stargate
            - 22 adept *2
            - 22 chrono @ core
            - 22 pylon
            - 22 nexus
            - 22 oracle
            - 22 chrono @ stargate
            - 22 adept *2
            - 22 pylon
            - 22 gateway
            - 22 oracle
            - 22 adept *2
            - 22 roboticsfacility
            - 22 gas
    AdeptVoidray:
        ConstantWorkerProductionTill: 44
        AutoSupplyAtSupply: 28
        OpeningBuildOrder:
            - 14 pylon @ ramp
            - 15 gate @ ramp
            - 15 chrono @ nexus
            - 16 gas
            - 15 worker_scout:
                [ enemy_spawn ]
            - 20 core @ ramp
            - 20 chrono @ nexus
            - 20 pylon
            - 20 gas
            - 20 nexus
            - 21 adept
            - 21 stargate
            - 24 warpgateresearch
            - 24 adept
            - 24 chrono @ gateway
            - 26 voidray
            - 26 chrono @ stargate
            - 24 adept
            - 30 twilightcouncil
            - 32 gateway *3
            - 32 adept
            - 32 adeptpiercingattack
            - 32 chrono @ twilightcouncil
            - 32 gateway
            - 32 pylon *2
            - 34 adept *3
            - 34 chrono @ twilightcouncil
            - 34 adept *5
            - 34 chrono @ twilightcouncil
            - 34 roboticsfacility
            - 34 adept *5

    OneBaseTempests:
        ConstantWorkerProductionTill: 22
        AutoSupplyAtSupply: 22
        OpeningBuildOrder:
            - 13 pylon @ ramp
            - 14 forge @ ramp
            - 15 chrono @ nexus
            - 16 gateway @ ramp
            - 16 gas
            - 16 photoncannon @ ramp
            - 16 gas
            - 16 pylon
            - 16 core
            - 16 photoncannon @ ramp
            - 16 pylon
            - 16 stargate
            - 16 shieldbattery @ ramp
            - 16 photoncannon @ ramp *2
            - 16 fleetbeacon
            - 16 photoncannon
            - 16 pylon *2
            - 16 tempest
            - 16 chrono @ stargate
            - 16 tempestgroundattackupgrade
            - 16 photoncannon
            - 16 shieldbattery

    PhoenixEconomic:
        # 1:26 - core starts, 320 min, 8 gas
        # 2:00 - adept starts, 95 min, 98 gas, 25 supply
        # 2:32 - stargate starts, 85min, 16 gas, 29 supply
        # 4:00 scout - if enemy expanded, and has 1/1/1
        # and extra production - we are safe
        ConstantWorkerProductionTill: 50
        AutoSupplyAtSupply: 44
        OpeningBuildOrder:
            - 13 pylon @ ramp
            - 14 gate @ ramp
            - 15 chrono @ nexus
            - 16 gas
            - 15 worker_scout:
                [ third, fourth, fifth, sixth ]
            - 19 core @ ramp
            - 19 pylon
            - 19 nexus
            - 21 adept
            - 21 chrono @ gateway
            - 21 gas
            - 20 adept
            - 20 chrono @ gateway
            - 20 stargate
            - 20 warpgateresearch
            - 20 stalker
            - 20 pylon @ nat
            - 20 phoenix
            - 20 chrono @ stargate
            - 20 gateway
            - 20 pylon
            - 20 phoenix
            - 20 chrono @ stargate
            - 20 gas
            - 20 gas
            - 20 phoenix
            - 20 nexus

